adlframework/__init__.py
adlframework/_dataentity.py
adlframework/cache.py
adlframework/datasource.py
adlframework/datasource_union.py
adlframework/experiment.py
adlframework/utils.py
adlframework/augmentations/__init__.py
adlframework/augmentations/general_augmentations.py
adlframework/augmentations/image_augmentations.py
adlframework/batch_updates/__init__.py
adlframework/batch_updates/gan_updates.py
adlframework/caches/__init__.py
adlframework/caches/nparr_cache.py
adlframework/callbacks/__init__.py
adlframework/callbacks/audio_callbacks.py
adlframework/callbacks/classification_callbacks.py
adlframework/callbacks/database_callbacks.py
adlframework/callbacks/general_callbacks.py
adlframework/callbacks/image_callbacks.py
adlframework/callbacks/planet_callbacks.py
adlframework/controllers/__init__.py
adlframework/controllers/arff/__init__.py
adlframework/controllers/audio/__init__.py
adlframework/controllers/audio/audio_callbacks.py
adlframework/controllers/audio/audio_nets.py
adlframework/controllers/audio/audio_processors.py
adlframework/controllers/audio/audio_samplers.py
adlframework/controllers/classification/__init__.py
adlframework/controllers/classification/classification_callbacks.py
adlframework/controllers/fits/__init__.py
adlframework/controllers/fits/planet_callbacks.py
adlframework/controllers/fits/planet_processors.py
adlframework/controllers/general/__init__.py
adlframework/controllers/general/general_augmentations.py
adlframework/controllers/general/general_filters.py
adlframework/controllers/general/general_metrics.py
adlframework/controllers/general/general_processors.py
adlframework/controllers/images/__init__.py
adlframework/controllers/images/image_augmentations.py
adlframework/controllers/images/image_callbacks.py
adlframework/controllers/lstm/__init__.py
adlframework/controllers/lstm/lstm_processors.py
adlframework/controllers/midis/__init__.py
adlframework/controllers/midis/midi_filters.py
adlframework-1.0.dist-info/DESCRIPTION.rst
adlframework-1.0.dist-info/METADATA
adlframework-1.0.dist-info/RECORD
adlframework-1.0.dist-info/WHEEL
adlframework-1.0.dist-info/metadata.json
adlframework-1.0.dist-info/top_level.txt
