Metadata-Version: 2.0
Name: adlframework
Version: 1.0
Summary: Deep learning Streamlined Process
Home-page: https://student.andover.edu
Author: George Alexander Reichenbach
Author-email: greichenbach@andover.edu
License: UNKNOWN
Download-URL: https://github.com/Reichenbachian/adlframework/archive/0.1.tar.gz
Keywords: deep learning,data framework,data,data manipulation,data augmentation
Platform: UNKNOWN
Requires-Dist: attr (==0.3.1)
Requires-Dist: attrs (==17.2.0)
Requires-Dist: Augmentor (==0.1.10)
Requires-Dist: backports-abc (==0.5)
Requires-Dist: backports.weakref (==1.0rc1)
Requires-Dist: bleach (==1.5.0)
Requires-Dist: boto (==2.48.0)
Requires-Dist: certifi (==2017.11.5)
Requires-Dist: config (==0.3.9)
Requires-Dist: Cython (==0.26.1)
Requires-Dist: decorator (==4.1.2)
Requires-Dist: funcsigs (==1.0.2)
Requires-Dist: future (==0.16.0)
Requires-Dist: glob2 (==0.6)
Requires-Dist: html5lib (==0.9999999)
Requires-Dist: IDLSave (==1.0.0)
Requires-Dist: imgaug (==0.2.5)
Requires-Dist: Keras (==2.0.6)
Requires-Dist: Markdown (==2.6.10)
Requires-Dist: matplotlib (==1.3.1)
Requires-Dist: mido (==1.2.8)
Requires-Dist: mock (==2.0.0)
Requires-Dist: music21 (==4.1.0)
Requires-Dist: networkx (==2.0)
Requires-Dist: nose (==1.3.7)
Requires-Dist: numexpr (==2.6.4)
Requires-Dist: numpy (==1.13.1)
Requires-Dist: olefile (==0.44)
Requires-Dist: opencv-python (==3.3.0.9)
Requires-Dist: pandas (==0.20.3)
Requires-Dist: pbr (==3.1.1)
Requires-Dist: Pillow (==4.3.0)
Requires-Dist: protobuf (==3.5.1)
Requires-Dist: psutil (==5.4.3)
Requires-Dist: pyparsing (==2.2.0)
Requires-Dist: python-dateutil (==2.6.1)
Requires-Dist: pytz (==2017.3)
Requires-Dist: PyWavelets (==0.5.2)
Requires-Dist: PyYAML (==3.12)
Requires-Dist: retrying (==1.3.3)
Requires-Dist: scikit-image (==0.13.1)
Requires-Dist: scikit-learn (==0.19.1)
Requires-Dist: scipy (==0.19.1)
Requires-Dist: singledispatch (==3.4.0.3)
Requires-Dist: six (==1.11.0)
Requires-Dist: tables (==3.4.2)
Requires-Dist: tensorflow (==1.2.1)
Requires-Dist: Theano (==1.0.1)
Requires-Dist: tornado (==4.5.2)
Requires-Dist: tqdm (==4.19.5)
Requires-Dist: Werkzeug (==0.13)
